{
    "name": "Grav\\Common\\GPM\\Remote\\AbstractPackageCollection",
    "line": 8,
    "short_desc": "",
    "long_desc": "",
    "hint": null,
    "tags": [],
    "namespace": "Grav\\Common\\GPM\\Remote",
    "file": "\/Users\/rhuk\/Projects\/grav\/grav-api\/..\/grav\/system\/src\/Grav\/Common\/GPM\/Remote\/AbstractPackageCollection.php",
    "relative_file": null,
    "hash": "58871dffe54b5a38035334c4fa805f699abeec33",
    "parent": "Grav\\Common\\GPM\\Common\\AbstractPackageCollection",
    "modifiers": "Stmt_Class",
    "is_trait": false,
    "is_interface": false,
    "aliases": {
        "BaseCollection": "Grav\\Common\\GPM\\Common\\AbstractPackageCollection",
        "Response": "Grav\\Common\\GPM\\Response",
        "FilesystemCache": "Doctrine\\Common\\Cache\\FilesystemCache"
    },
    "errors": [],
    "interfaces": [],
    "traits": [],
    "properties": [],
    "methods": {
        "__construct": {
            "name": "__construct",
            "line": 26,
            "short_desc": "Constructor to initialize array.",
            "long_desc": "",
            "hint": null,
            "hint_desc": null,
            "tags": [],
            "modifiers": "1",
            "is_by_ref": "",
            "exceptions": [],
            "errors": [],
            "parameters": {
                "repository": {
                    "name": "repository",
                    "line": 26,
                    "short_desc": null,
                    "long_desc": null,
                    "hint": null,
                    "tags": [],
                    "modifiers": "",
                    "default": "null",
                    "is_by_ref": false
                },
                "refresh": {
                    "name": "refresh",
                    "line": 26,
                    "short_desc": null,
                    "long_desc": null,
                    "hint": null,
                    "tags": [],
                    "modifiers": "",
                    "default": "false",
                    "is_by_ref": false
                },
                "callback": {
                    "name": "callback",
                    "line": 26,
                    "short_desc": null,
                    "long_desc": null,
                    "hint": null,
                    "tags": [],
                    "modifiers": "",
                    "default": "null",
                    "is_by_ref": false
                }
            }
        },
        "fetch": {
            "name": "fetch",
            "line": 44,
            "short_desc": "",
            "long_desc": "",
            "hint": null,
            "hint_desc": null,
            "tags": [],
            "modifiers": "1",
            "is_by_ref": "",
            "exceptions": [],
            "errors": [],
            "parameters": {
                "refresh": {
                    "name": "refresh",
                    "line": 44,
                    "short_desc": null,
                    "long_desc": null,
                    "hint": null,
                    "tags": [],
                    "modifiers": "",
                    "default": "false",
                    "is_by_ref": false
                },
                "callback": {
                    "name": "callback",
                    "line": 44,
                    "short_desc": null,
                    "long_desc": null,
                    "hint": null,
                    "tags": [],
                    "modifiers": "",
                    "default": "null",
                    "is_by_ref": false
                }
            }
        }
    },
    "constants": []
}